conflux_depthsim-0.1.0.dist-info/licenses/LICENSE
depthsim/__init__.py
depthsim/core.py
depthsim/models.py
depthsim/spread_models.py
conflux_depthsim-0.1.0.dist-info/METADATA
conflux_depthsim-0.1.0.dist-info/WHEEL
conflux_depthsim-0.1.0.dist-info/top_level.txt
conflux_depthsim-0.1.0.dist-info/RECORD
