Metadata-Version: 2.4
Name: conflux-depthsim
Version: 0.1.0
Summary: Professional order book depth simulation for backtesting and market analysis
Home-page: https://github.com/stefan-mcf/depthsim
Author: Conflux ML Engine Team
Author-email: Conflux ML Engine Team <noreply@conflux-ml.com>
License: MIT
Project-URL: Homepage, https://github.com/stefan-mcf/depthsim
Project-URL: Bug Reports, https://github.com/stefan-mcf/depthsim/issues
Project-URL: Source, https://github.com/stefan-mcf/depthsim
Project-URL: Documentation, https://github.com/stefan-mcf/depthsim#readme
Keywords: trading,backtesting,order-book,market-data,depth,simulation,finance,algorithmic-trading
Classifier: Development Status :: 4 - Beta
Classifier: Intended Audience :: Developers
Classifier: Intended Audience :: Financial and Insurance Industry
Classifier: Operating System :: OS Independent
Classifier: Programming Language :: Python :: 3
Classifier: Programming Language :: Python :: 3.8
Classifier: Programming Language :: Python :: 3.9
Classifier: Programming Language :: Python :: 3.10
Classifier: Programming Language :: Python :: 3.11
Classifier: Topic :: Office/Business :: Financial :: Investment
Classifier: Topic :: Scientific/Engineering :: Information Analysis
Classifier: Topic :: Software Development :: Libraries :: Python Modules
Requires-Python: >=3.8
License-File: LICENSE
Requires-Dist: numpy>=1.21.0
Requires-Dist: pandas>=1.3.0
Provides-Extra: dev
Requires-Dist: pytest>=7.0.0; extra == "dev"
Requires-Dist: pytest-cov>=4.0.0; extra == "dev"
Requires-Dist: black>=22.0.0; extra == "dev"
Requires-Dist: flake8>=5.0.0; extra == "dev"
Requires-Dist: mypy>=1.0.0; extra == "dev"
Requires-Dist: matplotlib>=3.5.0; extra == "dev"
Requires-Dist: jupyter>=1.0.0; extra == "dev"
Dynamic: author
Dynamic: home-page
Dynamic: license-file
Dynamic: requires-python
